econdatareader/__init__.py
econdatareader/bok.py
econdatareader/finance.py
econdatareader/fred.py
econdatareader/version.py
econ_datareader-1.0.5.dist-info/LICENSE
econ_datareader-1.0.5.dist-info/METADATA
econ_datareader-1.0.5.dist-info/WHEEL
econ_datareader-1.0.5.dist-info/top_level.txt
econ_datareader-1.0.5.dist-info/RECORD
