Metadata-Version: 2.1
Name: econ-datareader
Version: 1.0.5
Summary: Download Econ Data - Macro and Finance
Home-page: https://github.com/WYChoi1995/econ-datareader
Author: WyChoi1995
Author-email: wydanielchoi@gmail.com
Keywords: finance,economics
Classifier: Programming Language :: Python :: 3.6
Classifier: Programming Language :: Python :: 3.7
Classifier: Programming Language :: Python :: 3.8
Classifier: Programming Language :: Python :: 3.9
Classifier: Programming Language :: Python :: 3.10
Classifier: Programming Language :: Python :: 3.11
Requires-Python: >=3.6
License-File: LICENSE
Requires-Dist: pandas
Requires-Dist: aiohttp
Requires-Dist: nest-asyncio
